{
  "variant": {
    "label": "Debug",
    "keywordSettings": {
      "buildType": "debug"
    },
    "description": "Emit debug information without performing optimizations"
  },
  "activeEnvironments": [],
  "codeModel": {
    "configurations": [
      {
        "name": "Debug",
        "projects": [
          {
            "buildDirectory": "/home/ubuntu/github/ellcpp/build",
            "name": "ellcpp",
            "sourceDirectory": "/home/ubuntu/github/ellcpp",
            "targets": [
              {
                "artifacts": [
                  "/home/ubuntu/github/ellcpp/build/Main"
                ],
                "buildDirectory": "/home/ubuntu/github/ellcpp/build",
                "fileGroups": [
                  {
                    "compileFlags": "-g   -std=c++17 -pthread -std=gnu++1z",
                    "includePath": [
                      {
                        "path": "/media/ubuntu/casper-rw/miniconda2/include"
                      },
                      {
                        "path": "/home/ubuntu/github/ellcpp/third_party/benchmark/include"
                      }
                    ],
                    "isGenerated": false,
                    "language": "CXX",
                    "sources": [
                      "profit_main.cpp"
                    ]
                  }
                ],
                "fullName": "Main",
                "linkFlags": "-rdynamic",
                "linkLanguageFlags": "-g",
                "linkLibraries": "-L/media/ubuntu/casper-rw/miniconda2/include/../lib -llapack -lblas -lfmt -pthread",
                "linkerLanguage": "CXX",
                "name": "Main",
                "sourceDirectory": "/home/ubuntu/github/ellcpp",
                "type": "EXECUTABLE"
              },
              {
                "artifacts": [
                  "/home/ubuntu/github/ellcpp/build/Test"
                ],
                "buildDirectory": "/home/ubuntu/github/ellcpp/build",
                "fileGroups": [
                  {
                    "compileFlags": "-g   -std=c++17 -pthread -std=gnu++1z",
                    "includePath": [
                      {
                        "path": "/media/ubuntu/casper-rw/miniconda2/include"
                      },
                      {
                        "path": "/home/ubuntu/github/ellcpp/third_party/benchmark/include"
                      }
                    ],
                    "isGenerated": false,
                    "language": "CXX",
                    "sources": [
                      "exp1d.cpp"
                    ]
                  }
                ],
                "fullName": "Test",
                "linkFlags": "-rdynamic",
                "linkLanguageFlags": "-g",
                "linkLibraries": "-L/media/ubuntu/casper-rw/miniconda2/include/../lib -llapack -lblas -lfmt -pthread",
                "linkerLanguage": "CXX",
                "name": "Test",
                "sourceDirectory": "/home/ubuntu/github/ellcpp",
                "type": "EXECUTABLE"
              }
            ]
          }
        ]
      }
    ],
    "cookie": "0.2851239803819894",
    "inReplyTo": "codemodel",
    "type": "reply"
  }
}